ai_circuit_denoise-1.0.1.dist-info/licenses/LICENSE
circuit_denoiser/clean.py
circuit_denoiser/create_shortcut.py
circuit_denoiser/publish.py
circuit_denoiser/setup.py
circuit_denoiser/test_fix.py
ai_circuit_denoise-1.0.1.dist-info/METADATA
ai_circuit_denoise-1.0.1.dist-info/WHEEL
ai_circuit_denoise-1.0.1.dist-info/entry_points.txt
ai_circuit_denoise-1.0.1.dist-info/top_level.txt
ai_circuit_denoise-1.0.1.dist-info/RECORD
