Metadata-Version: 2.4
Name: ai-circuit-denoise
Version: 1.0.1
Summary: AI-based circuit image denoising tool for electronics engineers
Author-email: Your Name <your.email@example.com>
Project-URL: Homepage, https://github.com/yourusername/ai-circuit-denoise
Project-URL: Documentation, https://github.com/yourusername/ai-circuit-denoise/wiki
Project-URL: Source, https://github.com/yourusername/ai-circuit-denoise
Project-URL: Issues, https://github.com/yourusername/ai-circuit-denoise/issues
Keywords: circuit,denoise,ai,electronics,image-processing
Classifier: Development Status :: 4 - Beta
Classifier: Intended Audience :: Science/Research
Classifier: Intended Audience :: Education
Classifier: Intended Audience :: Manufacturing
Classifier: Topic :: Scientific/Engineering :: Electronic Design Automation (EDA)
Classifier: Topic :: Scientific/Engineering :: Image Processing
Classifier: License :: OSI Approved :: MIT License
Classifier: Programming Language :: Python :: 3
Classifier: Programming Language :: Python :: 3.7
Classifier: Programming Language :: Python :: 3.8
Classifier: Programming Language :: Python :: 3.9
Classifier: Programming Language :: Python :: 3.10
Classifier: Programming Language :: Python :: 3.11
Classifier: Operating System :: OS Independent
Classifier: Operating System :: Microsoft :: Windows
Classifier: Operating System :: MacOS :: MacOS X
Classifier: Operating System :: POSIX :: Linux
Requires-Python: >=3.7
License-File: LICENSE
Requires-Dist: PyQt5>=5.15.0
Requires-Dist: torch>=1.9.0
Requires-Dist: torchvision>=0.10.0
Requires-Dist: numpy>=1.21.0
Requires-Dist: opencv-python>=4.5.0
Requires-Dist: Pillow>=8.3.0
Requires-Dist: scikit-image>=0.18.0
Requires-Dist: matplotlib>=3.4.0
Provides-Extra: gpu
Requires-Dist: torch>=1.9.0; extra == "gpu"
Requires-Dist: torchvision>=0.10.0; extra == "gpu"
Provides-Extra: dev
Requires-Dist: pytest>=6.0; extra == "dev"
Requires-Dist: pytest-qt>=4.0; extra == "dev"
Requires-Dist: black>=21.0; extra == "dev"
Requires-Dist: flake8>=3.9; extra == "dev"
Provides-Extra: windows
Requires-Dist: pywin32>=300; extra == "windows"
Requires-Dist: winshell>=0.6; extra == "windows"
Dynamic: license-file
